{
  "preRequisites:11": [
    942
  ],
  "properties:10": {
    "betterquesting:10": {
      "desc:8": "No Description",
      "icon:10": {
        "Count:3": 1,
        "Damage:2": 32338,
        "id:8": "gtadditions:ga_meta_item"
      },
      "name:8": "Cosmic Computer",
      "visibility:8": "ALWAYS"
    }
  },
  "questID:3": 950,
  "tasks:9": {
    "0:10": {
      "autoConsume:1": 1,
      "index:3": 0,
      "requiredItems:9": {
        "0:10": {
          "Count:3": 1,
          "Damage:2": 32338,
          "id:8": "gtadditions:ga_meta_item"
        }
      },
      "taskID:8": "bq_standard:retrieval"
    }
  }
}