{
  "preRequisites:11": [
    413
  ],
  "properties:10": {
    "betterquesting:10": {
      "desc:8": "No Description",
      "icon:10": {
        "Count:3": 1,
        "id:8": "qmd:accelerator_vent"
      },
      "name:8": "Cooling Off"
    }
  },
  "questID:3": 414,
  "tasks:9": {
    "0:10": {
      "autoConsume:1": 1,
      "index:3": 0,
      "requiredItems:9": {
        "0:10": {
          "Count:3": 1,
          "id:8": "qmd:accelerator_vent"
        }
      },
      "taskID:8": "bq_standard:retrieval"
    }
  }
}